[
  {
    "_id": "68e0d5d6cef484f249f25937",
    "name": "Sharans Activated Charcoal Soap",
    "description": "Deep cleansing charcoal soap for healthy skin",
    "originalPrice": 249,
    "currentPrice": 149,
    "stock": 50,
    "category": "Bath & Body",
    "images": [
      "https://images.pexels.com/photos/4502069/pexels-photo-4502069.jpeg?auto=compress&cs=tinysrgb&w=600"
    ],
    "sku": "SOAP1002"
  },
  {
    "_id": "68e0d5d6cef484f249f25938",
    "name": "Organic Lavender Face Cream (50 ml)",
    "description": "Moisturizing cream with organic lavender extract",
    "originalPrice": 599,
    "currentPrice": 499,
    "stock": 40,
    "category": "Skincare",
    "images": [
      "https://images.pexels.com/photos/3762880/pexels-photo-3762880.jpeg?auto=compress&cs=tinysrgb&w=600"
    ],
    "sku": "CREAM1003"
  },
  {
    "_id": "68e0d5d6cef484f249f25939",
    "name": "Wireless Earbuds",
    "description": "Bluetooth 5.0 earbuds with noise cancellation",
    "originalPrice": 2999,
    "currentPrice": 2499,
    "stock": 25,
    "category": "Electronics",
    "images": [
      "https://images.pexels.com/photos/373945/pexels-photo-373945.jpeg?auto=compress&cs=tinysrgb&w=600"
    ],
    "sku": "EARBUDS1004"
  },
  {
    "_id": "68e0d5d6cef484f249f25940",
    "name": "Mechanical Keyboard",
    "description": "RGB mechanical keyboard with blue switches",
    "originalPrice": 2500,
    "currentPrice": 2200,
    "stock": 30,
    "category": "Electronics",
    "images": [
      "https://images.pexels.com/photos/787033/pexels-photo-787033.jpeg?auto=compress&cs=tinysrgb&w=600"
    ],
    "sku": "KEYBOARD1005"
  },
  {
    "_id": "68e0d5d6cef484f249f25941",
    "name": "Aloe Vera Face Wash",
    "description": "Gentle face wash with soothing aloe vera",
    "originalPrice": 399,
    "currentPrice": 299,
    "stock": 50,
    "category": "Skincare",
    "images": [
      "https://images.pexels.com/photos/3952034/pexels-photo-3952034.jpeg?auto=compress&cs=tinysrgb&w=600"
    ],
    "sku": "FACEWASH1006"
  },
  {
    "_id": "68e0d5d6cef484f249f25942",
    "name": "Vitamin C Serum",
    "description": "Brightening serum for glowing skin",
    "originalPrice": 899,
    "currentPrice": 799,
    "stock": 50,
    "category": "Skincare",
    "images": [
      "https://images.pexels.com/photos/3952229/pexels-photo-3952229.jpeg?auto=compress&cs=tinysrgb&w=600"
    ],
    "sku": "SERUM1007"
  },
  {
    "_id": "68e0d5d6cef484f249f25943",
    "name": "Coconut Hair Shampoo",
    "description": "Nourishing shampoo for smooth hair",
    "originalPrice": 499,
    "currentPrice": 399,
    "stock": 50,
    "category": "Hair Care",
    "images": [
      "https://images.pexels.com/photos/4640492/pexels-photo-4640492.jpeg?auto=compress&cs=tinysrgb&w=600"
    ],
    "sku": "SHAMPOO1008"
  },
  {
    "_id": "68e0d5d6cef484f249f25944",
    "name": "Herbal Body Lotion",
    "description": "Moisturizing lotion with natural herbs",
    "originalPrice": 599,
    "currentPrice": 499,
    "stock": 50,
    "category": "Bath & Body",
    "images": [
      "https://images.pexels.com/photos/4753620/pexels-photo-4753620.jpeg?auto=compress&cs=tinysrgb&w=600"
    ],
    "sku": "BODYLOTION1009"
  },
  {
    "_id": "68e0d5d6cef484f249f25945",
    "name": "Rose Water Toner",
    "description": "Refreshing toner with natural rose water",
    "originalPrice": 349,
    "currentPrice": 299,
    "stock": 50,
    "category": "Skincare",
    "images": [
      "https://images.pexels.com/photos/4149046/pexels-photo-4149046.jpeg?auto=compress&cs=tinysrgb&w=600"
    ],
    "sku": "TONER1010"
  },
  {
    "_id": "68e0d5d6cef484f249f25946",
    "name": "Tea Tree Oil Soap",
    "description": "Refreshing soap with tea tree oil",
    "originalPrice": 299,
    "currentPrice": 199,
    "stock": 40,
    "category": "Bath & Body",
    "images": [
      "https://images.pexels.com/photos/4502070/pexels-photo-4502070.jpeg?auto=compress&cs=tinysrgb&w=600"
    ],
    "sku": "SOAP1003"
  }
]
